task_mq-0.1.1.dist-info/licenses/LICENSE
taskmq/__init__.py
taskmq/api_server.py
taskmq/cli.py
taskmq/main.py
taskmq/worker.py
taskmq/jobs/__init__.py
taskmq/jobs/handlers.py
taskmq/storage/__init__.py
taskmq/storage/base.py
taskmq/storage/redis_backend.py
taskmq/storage/sqlite_backend.py
taskmq/utils/__init__.py
taskmq/utils/heartbeat.py
task_mq-0.1.1.dist-info/METADATA
task_mq-0.1.1.dist-info/WHEEL
task_mq-0.1.1.dist-info/entry_points.txt
task_mq-0.1.1.dist-info/top_level.txt
task_mq-0.1.1.dist-info/RECORD
