Metadata-Version: 2.4
Name: task-mq
Version: 0.1.1
Summary: Modern, developer-friendly Python task queue and job processing framework with CLI, API, and pluggable storage backends for scalable background job processing.
Home-page: https://github.com/gvarun01/task-mq
Author: Varun Gupta
Author-email: Varun Gupta <varungupta8976@gmail.com>
Maintainer-email: Varun Gupta <varungupta8976@gmail.com>
License:                                  Apache License
Project-URL: Homepage, https://github.com/gvarun01/task-mq
Project-URL: Repository, https://github.com/gvarun01/task-mq
Project-URL: Documentation, https://gvarun01.github.io/task-mq/
Project-URL: Issue Tracker, https://github.com/gvarun01/task-mq/issues
Project-URL: Changelog, https://github.com/gvarun01/task-mq/releases
Keywords: task-queue,job-processing,background-jobs,worker,async,scheduler,cli,api,fastapi,prometheus,sqlite,redis
Classifier: Development Status :: 4 - Beta
Classifier: Intended Audience :: Developers
Classifier: License :: OSI Approved :: MIT License
Classifier: Operating System :: OS Independent
Classifier: Programming Language :: Python :: 3
Classifier: Programming Language :: Python :: 3.8
Classifier: Programming Language :: Python :: 3.9
Classifier: Programming Language :: Python :: 3.10
Classifier: Programming Language :: Python :: 3.11
Classifier: Programming Language :: Python :: 3.12
Classifier: Topic :: Software Development :: Libraries :: Python Modules
Classifier: Topic :: System :: Distributed Computing
Classifier: Topic :: Internet :: WWW/HTTP :: HTTP Servers
Classifier: Framework :: FastAPI
Requires-Python: >=3.8
License-File: LICENSE
Requires-Dist: fastapi>=0.68.0
Requires-Dist: prometheus_client>=0.12.0
Requires-Dist: python-jose[cryptography]>=3.3.0
Requires-Dist: click>=8.0.0
Requires-Dist: PyJWT>=2.4.0
Requires-Dist: uvicorn[standard]>=0.15.0
Provides-Extra: dev
Requires-Dist: pytest>=6.0; extra == "dev"
Requires-Dist: httpx>=0.24.0; extra == "dev"
Requires-Dist: pytest-cov>=3.0.0; extra == "dev"
Requires-Dist: black>=22.0.0; extra == "dev"
Requires-Dist: isort>=5.10.0; extra == "dev"
Requires-Dist: flake8>=4.0.0; extra == "dev"
Requires-Dist: mypy>=0.910; extra == "dev"
Provides-Extra: test
Requires-Dist: pytest>=6.0; extra == "test"
Requires-Dist: httpx>=0.24.0; extra == "test"
Requires-Dist: pytest-cov>=3.0.0; extra == "test"
Provides-Extra: redis
Requires-Dist: redis>=4.0.0; extra == "redis"
Provides-Extra: docs
Requires-Dist: mkdocs>=1.4.0; extra == "docs"
Requires-Dist: mkdocs-material>=8.0.0; extra == "docs"
Dynamic: author
Dynamic: home-page
Dynamic: license-file
Dynamic: requires-python
